{"baseVals":{"rating":0,"gammaadj":1,"decay":1,"echo_zoom":1,"echo_alpha":1,"echo_orient":1,"wave_mode":5,"wave_brighten":0,"wave_a":0.001,"wave_scale":1.447722,"wave_smoothing":0.5,"modwavealphastart":0.5,"modwavealphaend":1,"fshader":1,"dx":0.00001,"dy":0.00001,"warp":0.01,"wave_r":0.5,"wave_g":0.5,"wave_b":0.5,"ob_size":0.015,"ob_a":1,"ib_r":0,"ib_g":0,"ib_b":0,"ib_a":1,"mv_x":0,"mv_y":0,"mv_l":1,"mv_a":0},"shapes":[{"baseVals":{"enabled":0}},{"baseVals":{"enabled":0}},{"baseVals":{"enabled":0}},{"baseVals":{"enabled":0}}],"waves":[{"baseVals":{"enabled":0}},{"baseVals":{"enabled":0}},{"baseVals":{"enabled":0}},{"baseVals":{"enabled":0}}],"init_eqs_str":"m.pfdx_r = 0;\nm.pfthresh = 0;\nm.thresh = 0;\nm.ladder = 0;\nm.q1 = 0;\nm.leafset = 0;\nm.dy_r = 0;\nm.pfdy_r = 0;\nm.leaf = 0;\nm.dx_r = 0;\nm.q2 = 0;\nm.q3 = 0;\nm.leafset=3;","frame_eqs_str":"m.wave_r=(0.5+(0.5*Math.sin((1.6*m.time)))); m.wave_g=(0.5+(0.5*Math.sin((4.1*m.time)))); m.wave_b=(-1+(((1-m.wave_r)+1)-m.wave_g)); m.warp=0; m.pfthresh=((above(m.bass_att, m.pfthresh)*3)+((1-above(m.bass_att, m.pfthresh))*(((m.pfthresh-1.3)*0.96)+1.3))); m.pfdx_r=(((equal(m.pfthresh, 3)*0.015)*Math.sin((5*m.time)))+((1-equal(m.pfthresh, 3))*m.pfdx_r)); m.pfdy_r=(((equal(m.pfthresh, 3)*0.015)*Math.sin((6*m.time)))+((1-equal(m.pfthresh, 3))*m.pfdy_r)); m.q1=m.wave_r; m.q2=m.wave_g; m.q3=m.wave_b; m.ob_r=(1-(Math.abs(m.q1)*0.75)); m.ob_g=(1-(Math.abs(m.q2)*0.75)); m.ob_b=(1-(Math.abs(m.q3)*0.75)); m.echo_zoom=(m.echo_zoom+Math.min(Math.max(0.75, (50*m.pfdx_r)), 1)); m.echo_orient=(m.echo_orient+(16*m.pfdy_r)); m.dx=(m.dx+(15.1*m.pfdx_r)); m.dy=(m.dy+(15.1*m.pfdy_r)); m.ob_size=(m.ob_size+(0.005*m.bass_att)); m.ib_a=(m.ib_a-Math.min(0.5, (0.5-Math.abs((m.dx+m.dy)))));\n\t\tm.rkeys = ['thresh','dx_r','dy_r','leafset','zoom'];","pixel_eqs_str":"m.thresh=((above(m.bass_att, m.thresh)*2)+((1-above(m.bass_att, m.thresh))*(((m.thresh-1.3)*0.96)+1.3))); m.dx_r=(((equal(m.thresh, 2)*0.015)*Math.sin((5*m.time)))+((1-equal(m.thresh, 2))*m.dx_r)); m.dy_r=(((equal(m.thresh, 2)*0.015)*Math.sin((6*m.time)))+((1-equal(m.thresh, 2))*m.dy_r)); m.ladder=Math.abs(Math.sin((1*m.time))); m.leaf=(((((5*below(m.ladder, 0.2))+((8*above(m.ladder, 0.2))*below(m.ladder, 0.4)))+((12*above(m.ladder, 0.4))*below(m.ladder, 0.6)))+((18*above(m.ladder, 0.6))*below(m.ladder, 0.8)))+(24*above(m.ladder, 0.8))); m.leafset=((equal(m.thresh, 2)!=0)?(m.leaf):(m.leafset)); m.zoom=(m.zoom+((0.05*(0.75-Math.cos((m.leafset*m.rad))))*(1-m.rad))); m.zoom=(m.zoom-Math.abs((0.05*(0.75-Math.cos((4*m.rad))))));","warp":"","comp":""}