{"baseVals":{"rating":5,"gammaadj":1,"decay":0.9,"echo_zoom":1,"echo_alpha":0,"echo_orient":3,"wave_mode":6,"additivewave":0,"wave_dots":0,"wave_thick":0,"modwavealphabyvolume":0,"wave_brighten":0,"wrap":1,"darken_center":0,"red_blue":0,"brighten":0,"darken":0,"solarize":0,"invert":0,"wave_a":0.005,"wave_scale":0.167,"wave_smoothing":0,"wave_mystery":0,"modwavealphastart":1,"modwavealphaend":1,"warpanimspeed":1,"warpscale":0.107,"zoomexp":1.0018,"fshader":1,"zoom":0.96098,"rot":0,"cx":0.5,"cy":0.5,"dx":0,"dy":0,"warp":0.01,"sx":1,"sy":1,"wave_r":1,"wave_g":1,"wave_b":1,"wave_x":0.95,"wave_y":1,"ob_size":0.005,"ob_r":1,"ob_g":0,"ob_b":0,"ob_a":1,"ib_size":0,"ib_r":1,"ib_g":1,"ib_b":1,"ib_a":1,"mv_x":64,"mv_y":48,"mv_dx":-0.002,"mv_dy":0,"mv_l":0,"mv_r":1,"mv_g":0,"mv_b":0,"mv_a":0,"b1n":0,"b2n":0,"b3n":0,"b1x":1,"b2x":1,"b3x":1,"b1ed":0},"shapes":[{"baseVals":{"enabled":0,"sides":100,"additive":0,"thickoutline":1,"textured":0,"num_inst":1,"x":0.5,"y":0.5,"rad":0.42324,"ang":0,"tex_ang":0,"tex_zoom":0.5033,"r":1,"g":0,"b":0,"a":1,"r2":1,"g2":1,"b2":1,"a2":0,"border_r":1,"border_g":1,"border_b":1,"border_a":0},"init_eqs_str":"m.t = 0;\nm.q4 = 0;\nm.q5 = 0;\nm.vx=0; m.vy=0;\n\t\t\tm.rkeys = [];","frame_eqs_str":"m.t=(-(m.q4+m.q5)*0.2); m.x=(0.5+(Math.sin(m.t)*0.2)); m.y=(0.5+(Math.cos(m.t)*0.1)); m.rad=(0.4-(Math.cos(m.t)*0.3));"},{"baseVals":{"enabled":0,"sides":100,"additive":0,"thickoutline":1,"textured":0,"num_inst":1,"x":0.5,"y":0.5,"rad":0.42324,"ang":0,"tex_ang":0,"tex_zoom":0.5033,"r":0,"g":0,"b":1,"a":1,"r2":1,"g2":1,"b2":1,"a2":0,"border_r":1,"border_g":1,"border_b":1,"border_a":0},"init_eqs_str":"m.t = 0;\nm.pi = 0;\nm.q4 = 0;\nm.q5 = 0;\nm.vx=0; m.vy=0;\n\t\t\tm.rkeys = [];","frame_eqs_str":"m.t=(-(m.q4+m.q5)*0.2); m.pi=(Math.asin(1)*2); m.x=(0.5+(Math.sin((m.t+m.pi))*0.2)); m.y=(0.5+(Math.cos((m.t+m.pi))*0.1)); m.rad=(0.4-(Math.cos((m.t+m.pi))*0.3));"},{"baseVals":{"enabled":0,"sides":4,"additive":0,"thickoutline":1,"textured":0,"num_inst":1,"x":1,"y":0.5,"rad":1.00591,"ang":0,"tex_ang":0,"tex_zoom":0.5033,"r":0,"g":0,"b":1,"a":1,"r2":0,"g2":0,"b2":1,"a2":1,"border_r":1,"border_g":1,"border_b":1,"border_a":0},"init_eqs_str":"m.q3 = 0;\nm.vx=0; m.vy=0;\n\t\t\tm.rkeys = [];","frame_eqs_str":"m.x=1.2; m.y=(m.q3-0.4);"},{"baseVals":{"enabled":0,"sides":100,"additive":0,"thickoutline":0,"textured":0,"num_inst":1,"x":0.5,"y":0.5,"rad":0.99595,"ang":0,"tex_ang":0,"tex_zoom":1,"r":0,"g":0,"b":0,"a":0.1,"r2":1,"g2":1,"b2":1,"a2":1,"border_r":1,"border_g":1,"border_b":1,"border_a":0},"init_eqs_str":"m.q6 = 0;\nm.q1 = 0;\nm.q5 = 0;\nm.pi3 = 0;\nm.q4 = 0;\nm.t = 0;\nm.q2 = 0;\nm.q3 = 0;\nm.c = 0;\n\n\t\t\tm.rkeys = [];","frame_eqs_str":"m.rad=(0.5+(((m.q1-m.q2)+m.q3)*1)); m.ang=(-(m.q4-m.q5)*0.2); m.pi3=((3.1415*2)*0.3333); m.t=(((m.q4-(2*m.q5))+m.q6)*0.2); m.c=3; m.r=(Math.sin(m.t)*m.c); m.g=(Math.sin((m.t+m.pi3))*m.c); m.b=(Math.sin((m.t-m.pi3))*m.c); m.r=((above(m.r, 1)!=0)?(1):(m.r)); m.r=((below(m.r, 0)!=0)?(0):(m.r)); m.g=((above(m.g, 1)!=0)?(1):(m.g)); m.g=((below(m.g, 0)!=0)?(0):(m.g)); m.b=((above(m.b, 1)!=0)?(1):(m.b)); m.b=((below(m.b, 0)!=0)?(0):(m.b)); m.r2=(1-m.r); m.g2=(1-m.g); m.b2=(1-m.b);"}],"waves":[{"baseVals":{"enabled":0,"samples":457,"sep":0,"spectrum":0,"usedots":0,"thick":1,"additive":0,"scaling":3.80064,"smoothing":1,"r":0,"g":1,"b":0,"a":1},"init_eqs_str":"m.d = 0;\nm.xx = 0;\nm.z = 0;\nm.w = 0;\nm.t5 = 0;\nm.t1 = 0;\nm.q6 = 0;\nm.zoom = 0;\nm.p = 0;\nm.q1 = 0;\nm.q5 = 0;\nm.t8 = 0;\nm.t3 = 0;\nm.t6 = 0;\nm.pi3 = 0;\nm.q4 = 0;\nm.dir = 0;\nm.zm = 0;\nm.t = 0;\nm.zz = 0;\nm.t2 = 0;\nm.q2 = 0;\nm.q3 = 0;\nm.t4 = 0;\nm.yy = 0;\nm.c = 0;\nm.t8=1;\n\t\t\tm.rkeys = ['t8'];","frame_eqs_str":"m.t1=m.q1; m.t2=m.q2; m.t3=m.q3; m.t4=m.q4; m.t5=m.q5; m.t6=m.q6; m.pi3=((3.1415*2)*0.3333); m.t=(((m.q4+m.q5)+m.q6)*0.005); m.c=5; m.r=(1-(Math.sin(m.t)*m.c)); m.g=(1-(Math.sin((m.t+m.pi3))*m.c)); m.b=(1-(Math.sin((m.t-m.pi3))*m.c)); m.r=((above(m.r, 1)!=0)?(1):(m.r)); m.r=((below(m.r, 0)!=0)?(0):(m.r)); m.g=((above(m.g, 1)!=0)?(1):(m.g)); m.g=((below(m.g, 0)!=0)?(0):(m.g)); m.b=((above(m.b, 1)!=0)?(1):(m.b)); m.b=((below(m.b, 0)!=0)?(0):(m.b));","point_eqs_str":"m.t8=-m.t8; m.d=sqrt((1-sqr(((m.sample-0.5)*2)))); m.z=((m.sample*0.4)-0.2); m.x=((Math.sin((m.sample*100))*m.d)*0.2); m.y=((Math.cos((m.sample*100))*m.d)*0.2); m.p=0.1; m.x=(m.x*(1+(m.t8*m.p))); m.y=(m.y*(1+(m.t8*m.p))); m.z=(m.z*(1+(m.t8*m.p))); m.dir=(((m.t4-m.t6)*0.4)+(((m.t1-m.t3)*(m.t8+1))*0.2)); m.d=(2+pow(m.t2, 3)); m.w=((m.t5*0.4)+(((m.t8+1)*m.t2)*0.2)); m.zz=m.z; m.yy=m.y; m.y=((Math.cos(m.w)*m.yy)-(Math.sin(m.w)*m.zz)); m.z=((Math.sin(m.w)*m.yy)+(Math.cos(m.w)*m.zz)); m.xx=((Math.cos(m.dir)*m.x)-(Math.sin(m.dir)*m.y)); m.yy=((Math.sin(m.dir)*m.x)+(Math.cos(m.dir)*m.y)); m.d=0.5; m.zoom=(2-(sqrt(m.t2)*1.1)); m.zm=div(sqrt((((m.x*m.x)+(m.y*m.y))+sqr((m.z+m.d)))),m.d); m.x=(0.5+div(((m.zoom*m.xx)*0.55),m.zm)); m.y=(0.5+div(((m.zoom*m.yy)*0.55),m.zm)); m.a=sigmoid((-m.z+0.1), 25);"},{"baseVals":{"enabled":0,"samples":457,"sep":0,"spectrum":0,"usedots":1,"thick":1,"additive":0,"scaling":3.80064,"smoothing":1,"r":0,"g":1,"b":0,"a":1},"init_eqs_str":"m.d = 0;\nm.xx = 0;\nm.z = 0;\nm.w = 0;\nm.t5 = 0;\nm.t1 = 0;\nm.q6 = 0;\nm.zoom = 0;\nm.p = 0;\nm.q1 = 0;\nm.q5 = 0;\nm.t8 = 0;\nm.t3 = 0;\nm.t6 = 0;\nm.pi3 = 0;\nm.q4 = 0;\nm.dir = 0;\nm.zm = 0;\nm.t = 0;\nm.zz = 0;\nm.t2 = 0;\nm.q2 = 0;\nm.q3 = 0;\nm.t4 = 0;\nm.yy = 0;\nm.c = 0;\nm.t8=1;\n\t\t\tm.rkeys = ['t8'];","frame_eqs_str":"m.t1=m.q1; m.t2=m.q2; m.t3=m.q3; m.t4=m.q4; m.t5=m.q5; m.t6=m.q6; m.pi3=((3.1415*2)*0.3333); m.t=((((m.q4+m.q5)+m.q6)*0.005)+2); m.c=5; m.r=(1-(Math.sin(m.t)*m.c)); m.g=(1-(Math.sin((m.t+m.pi3))*m.c)); m.b=(1-(Math.sin((m.t-m.pi3))*m.c)); m.r=((above(m.r, 1)!=0)?(1):(m.r)); m.r=((below(m.r, 0)!=0)?(0):(m.r)); m.g=((above(m.g, 1)!=0)?(1):(m.g)); m.g=((below(m.g, 0)!=0)?(0):(m.g)); m.b=((above(m.b, 1)!=0)?(1):(m.b)); m.b=((below(m.b, 0)!=0)?(0):(m.b));","point_eqs_str":"m.t8=-m.t8; m.d=sqrt((1-sqr(((m.sample-0.5)*2)))); m.z=((m.sample*0.4)-0.2); m.x=((Math.sin((m.sample*100))*m.d)*0.2); m.y=((Math.cos((m.sample*100))*m.d)*0.2); m.p=0.1; m.x=(m.x*(1+(m.t8*m.p))); m.y=(m.y*(1+(m.t8*m.p))); m.z=(m.z*(1+(m.t8*m.p))); m.dir=(((m.t4-m.t6)*0.4)+(((m.t1-m.t3)*(m.t8+1))*0.2)); m.d=(2+pow(m.t2, 3)); m.w=((m.t5*0.4)+(((m.t8+1)*m.t2)*0.2)); m.zz=m.z; m.yy=m.y; m.y=((Math.cos(m.w)*m.yy)-(Math.sin(m.w)*m.zz)); m.z=((Math.sin(m.w)*m.yy)+(Math.cos(m.w)*m.zz)); m.xx=((Math.cos(m.dir)*m.x)-(Math.sin(m.dir)*m.y)); m.yy=((Math.sin(m.dir)*m.x)+(Math.cos(m.dir)*m.y)); m.d=0.5; m.zoom=(2-(sqrt(m.t2)*1.1)); m.zm=div(sqrt((((m.x*m.x)+(m.y*m.y))+sqr((m.z+m.d)))),m.d); m.x=(0.5+div(((m.zoom*m.xx)*0.55),m.zm)); m.y=(0.5+div(((m.zoom*m.yy)*0.55),m.zm)); m.a=sigmoid((-m.z+0.1), 25);"},{"baseVals":{"enabled":0,"samples":512,"sep":4,"spectrum":0,"usedots":0,"thick":1,"additive":1,"scaling":1.37242,"smoothing":1,"r":1,"g":1,"b":1,"a":1},"init_eqs_str":"m.d = 0;\nm.n = 0;\nm.y1 = 0;\nm.xx = 0;\nm.z = 0;\nm.w = 0;\nm.s = 0;\nm.t5 = 0;\nm.t1 = 0;\nm.x1 = 0;\nm.q6 = 0;\nm.zoom = 0;\nm.q1 = 0;\nm.q5 = 0;\nm.j = 0;\nm.d1 = 0;\nm.t3 = 0;\nm.s8 = 0;\nm.t6 = 0;\nm.pi3 = 0;\nm.q4 = 0;\nm.c2 = 0;\nm.s3 = 0;\nm.t = 0;\nm.zz = 0;\nm.c3 = 0;\nm.t2 = 0;\nm.q2 = 0;\nm.q3 = 0;\nm.s1 = 0;\nm.s2 = 0;\nm.m = 0;\nm.t4 = 0;\nm.yy = 0;\nm.c = 0;\nm.c1 = 0;\nm.t2=0; m.t3=0; m.t4=0; m.ab=1;\n\t\t\tm.rkeys = [];","frame_eqs_str":"m.t1=(m.q1*0.5); m.t2=(m.q2*0.5); m.t3=(m.q3*0.5); m.t4=m.q4; m.t5=m.q5; m.t6=m.q6;","point_eqs_str":"m.s8=(m.sample*383); m.s=0.3; m.xx=(((mod((m.sample*343),7)-3.5)*m.s)+m.value1); m.yy=(((mod((m.sample*49),7)-3.5)*m.s)*0.5); m.zz=(((mod((m.sample*7),7)-3.5)*m.s)*0.5); m.n=300; m.xx=((-0.5+m.sample)*2); m.zz=(Math.cos((m.sample*m.n))*0.02); m.yy=(Math.sin((m.sample*m.n))*0.02); m.d=sqrt((((m.xx*m.xx)+(m.yy*m.yy))+(m.zz*m.zz))); m.d1=1; m.xx=((m.xx*m.d1)*(1+m.value1)); m.yy=((m.yy*m.d1)*(1+m.value2)); m.zz=(m.zz*m.d1); m.w=0.3; m.m=((m.d*m.d)*2); m.s1=Math.sin(((m.t4*m.w)+(m.m*m.t1))); m.s2=Math.sin(((m.t5*m.w)+(m.m*m.t2))); m.s3=Math.sin(((m.t6*m.w)+(m.m*m.t3))); m.c1=Math.cos(((m.t4*m.w)+(m.m*m.t1))); m.c2=Math.cos(((m.t5*m.w)+(m.m*m.t2))); m.c3=Math.cos(((m.t6*m.w)+(m.m*m.t3))); m.z=((((((m.c3*m.s1)*m.c2)+(m.s3*m.s2))*m.xx)-((((m.c3*m.s1)*m.s2)-(m.s3*m.c2))*m.yy))+((m.c3*m.c1)*m.zz)); m.x1=((((m.c1*m.c2)*m.xx)+((m.c1*m.s2)*m.yy))-(m.s1*m.zz)); m.y1=((((((m.s3*m.s1)*m.c2)-(m.c3*m.s2))*m.xx)+((((m.s3*m.s1)*m.s2)+(m.c3*m.c2))*m.yy))+((m.s3*m.c1)*m.zz)); m.a=2; m.zoom=(0.3*Math.atan2((m.a-m.z), m.a)); m.x=(0.5+(m.zoom*m.x1)); m.y=(0.5+(m.zoom*m.y1)); m.pi3=((3.1415*2)*0.3333); m.t=(-m.xx+(m.t5*0.2)); m.c=10; m.r=(Math.sin(m.t)*m.c); m.g=(Math.sin((m.t+m.pi3))*m.c); m.b=(Math.sin((m.t-m.pi3))*m.c); m.j=0.81; m.r=((above(m.r, 1)!=0)?(1):(m.r)); m.r=((below(m.r, 0)!=0)?(0):(m.r)); m.g=((above(m.g, 1)!=0)?(1):(m.g)); m.g=((below(m.g, 0)!=0)?(0):(m.g)); m.b=((above(m.b, 1)!=0)?(1):(m.b)); m.b=((below(m.b, 0)!=0)?(0):(m.b)); m.a=2;"},{"baseVals":{"enabled":0,"samples":512,"sep":4,"spectrum":0,"usedots":0,"thick":1,"additive":1,"scaling":1.37242,"smoothing":1,"r":1,"g":1,"b":1,"a":1},"init_eqs_str":"m.d = 0;\nm.n = 0;\nm.y1 = 0;\nm.xx = 0;\nm.z = 0;\nm.w = 0;\nm.s = 0;\nm.t5 = 0;\nm.t1 = 0;\nm.x1 = 0;\nm.q6 = 0;\nm.zoom = 0;\nm.q1 = 0;\nm.q5 = 0;\nm.j = 0;\nm.d1 = 0;\nm.t3 = 0;\nm.s8 = 0;\nm.t6 = 0;\nm.pi3 = 0;\nm.q4 = 0;\nm.c2 = 0;\nm.s3 = 0;\nm.t = 0;\nm.zz = 0;\nm.c3 = 0;\nm.t2 = 0;\nm.q2 = 0;\nm.q3 = 0;\nm.s1 = 0;\nm.s2 = 0;\nm.m = 0;\nm.t4 = 0;\nm.yy = 0;\nm.c = 0;\nm.c1 = 0;\nm.t2=0; m.t3=0; m.t4=0; m.ab=1;\n\t\t\tm.rkeys = [];","frame_eqs_str":"m.t1=(m.q1*0.5); m.t2=(m.q2*0.5); m.t3=(m.q3*0.5); m.t4=m.q4; m.t5=m.q5; m.t6=m.q6;","point_eqs_str":"m.s8=(m.sample*383); m.s=0.3; m.xx=(((mod((m.sample*343),7)-3.5)*m.s)+m.value1); m.yy=(((mod((m.sample*49),7)-3.5)*m.s)*0.5); m.zz=(((mod((m.sample*7),7)-3.5)*m.s)*0.5); m.n=300; m.zz=((-0.5+m.sample)*2); m.xx=(Math.cos((m.sample*m.n))*0.02); m.yy=(Math.sin((m.sample*m.n))*0.02); m.d=sqrt((((m.xx*m.xx)+(m.yy*m.yy))+(m.zz*m.zz))); m.d1=1; m.xx=((m.xx*m.d1)*(1+m.value1)); m.yy=((m.yy*m.d1)*(1+m.value2)); m.zz=(m.zz*m.d1); m.w=0.3; m.m=((m.d*m.d)*2); m.s1=Math.sin(((m.t4*m.w)+(m.m*m.t1))); m.s2=Math.sin(((m.t5*m.w)+(m.m*m.t2))); m.s3=Math.sin(((m.t6*m.w)+(m.m*m.t3))); m.c1=Math.cos(((m.t4*m.w)+(m.m*m.t1))); m.c2=Math.cos(((m.t5*m.w)+(m.m*m.t2))); m.c3=Math.cos(((m.t6*m.w)+(m.m*m.t3))); m.z=((((((m.c3*m.s1)*m.c2)+(m.s3*m.s2))*m.xx)-((((m.c3*m.s1)*m.s2)-(m.s3*m.c2))*m.yy))+((m.c3*m.c1)*m.zz)); m.x1=((((m.c1*m.c2)*m.xx)+((m.c1*m.s2)*m.yy))-(m.s1*m.zz)); m.y1=((((((m.s3*m.s1)*m.c2)-(m.c3*m.s2))*m.xx)+((((m.s3*m.s1)*m.s2)+(m.c3*m.c2))*m.yy))+((m.s3*m.c1)*m.zz)); m.a=2; m.zoom=(0.3*Math.atan2((m.a-m.z), m.a)); m.x=(0.5+(m.zoom*m.x1)); m.y=(0.5+(m.zoom*m.y1)); m.pi3=((3.1415*2)*0.3333); m.t=(-m.zz+(m.t6*0.2)); m.c=10; m.r=(Math.sin(m.t)*m.c); m.g=(Math.sin((m.t+m.pi3))*m.c); m.b=(Math.sin((m.t-m.pi3))*m.c); m.j=0.81; m.r=((above(m.r, 1)!=0)?(1):(m.r)); m.r=((below(m.r, 0)!=0)?(0):(m.r)); m.g=((above(m.g, 1)!=0)?(1):(m.g)); m.g=((below(m.g, 0)!=0)?(0):(m.g)); m.b=((above(m.b, 1)!=0)?(1):(m.b)); m.b=((below(m.b, 0)!=0)?(0):(m.b)); m.a=2;"}],"init_eqs_str":"m.d = 0;\nm.xx = 0;\nm.w = 0;\nm.ww = 0;\nm.vt = 0;\nm.xh = 0;\nm.q6 = 0;\nm.q1 = 0;\nm.q5 = 0;\nm.vb = 0;\nm.q9 = 0;\nm.v = 0;\nm.ax = 0;\nm.mm = 0;\nm.tt = 0;\nm.yh = 0;\nm.wv = 0;\nm.vx = 0;\nm.pi = 0;\nm.vy = 0;\nm.ry = 0;\nm.q4 = 0;\nm.ddy = 0;\nm.rx = 0;\nm.ay = 0;\nm.t = 0;\nm.wh = 0;\nm.bb = 0;\nm.ddx = 0;\nm.q2 = 0;\nm.q3 = 0;\nm.m = 0;\nm.vvm = 0;\nm.yy = 0;\nm.vvb = 0;\nm.q7 = 0;\nm.vm = 0;\nm.vvt = 0;\nm.q8 = 0;\nm.x1=0; m.y1=0;","frame_eqs_str":"m.vb=((m.vb*0.95)+(((1-m.vb)*pow(m.bass, 2))*0.02)); m.vvb=((m.vvb*0.95)+(((1-m.vvb)*m.vb)*0.01)); m.vm=((m.vm*0.95)+(((1-m.vm)*pow(m.mid, 2))*0.02)); m.vvm=((m.vvm*0.95)+(((1-m.vvm)*m.vm)*0.01)); m.vt=((m.vt*0.95)+(((1-m.vt)*pow(m.treb, 2))*0.02)); m.vvt=((m.vvt*0.95)+(((1-m.vvt)*m.vt)*0.01)); m.vvb=Math.min(1, Math.max(0, m.vvb)); m.vvm=Math.min(1, Math.max(0, m.vvm)); m.vvt=Math.min(1, Math.max(0, m.vvt)); m.q1=(m.vvb*2); m.q2=(m.vvm*2); m.q3=(m.vvt*2); m.v=2; m.bb=(m.bb-(m.vvb*m.v)); m.mm=(m.mm-(m.vvm*m.v)); m.tt=(m.tt-(m.vvt*m.v)); m.q4=m.bb; m.q5=m.mm; m.q6=m.tt; m.q7=1.81; m.q8=(0.448+((m.vm-m.vt)*0.3)); m.q9=(0.701+((m.vb-m.vm)*0.3));\n\t\tm.rkeys = ['ax','ay'];","pixel_eqs_str":"m.pi=Math.asin(1); m.x=(m.x-0.5); m.y=(m.y-0.5); m.d=((((m.q4-m.q6)*0.4)+(((m.rad-0.3)*(m.q1-m.q3))*2))+m.pi); m.xx=((Math.sin(m.d)*m.x)-(Math.cos(m.d)*m.y)); m.yy=((Math.cos(m.d)*m.x)+(Math.sin(m.d)*m.y)); m.x=m.xx; m.y=m.yy; m.t=(m.time*0); m.xh=m.x; m.yh=m.y; m.w=((m.q4-m.q6)*0.8); m.m=(-1+(m.q2*2)); m.wv=(m.pi-(Math.sin(m.w)*m.m)); m.wh=(m.pi-(Math.cos(m.w)*m.m)); m.d=(6*sqrt(m.q2)); m.ww=1.1; m.ddx=Math.sin((((2*m.pi)-m.wv)-(m.x*m.ww))); m.ddy=Math.sin((((2*m.pi)-m.wh)-(m.y*m.ww))); m.rx=((above((m.ddx*m.ddy), 0)!=0)?(div(Math.sin(m.wv),m.ddx)):(0)); m.ry=((above((m.ddy*m.ddy), 0)!=0)?(div(Math.sin(m.wh),m.ddy)):(0)); m.v=div((((-m.q2*0.04)*div(m.d,m.ww))*1728),(m.meshx*m.meshy)); m.ax=(m.ax+(Math.sin(m.w)*m.v)); m.ay=(m.ay+(Math.cos(m.w)*m.v)); m.vx=((equal((m.rx*m.ry), 0)!=0)?(0):(m.ax)); m.vy=((equal((m.rx*m.ry), 0)!=0)?(0):(m.ay)); m.dx=((((-m.xh*m.rx)*m.ry)*m.d)+(m.vx*0.001)); m.dy=((((-m.yh*m.rx)*m.ry)*m.d)+(m.vy*0.001));","warp":"shader_body\n{\n  vec2 x_1;\n  x_1 = (uv_orig - 0.5);\n  vec4 tmpvar_2;\n  tmpvar_2.w = 0.0;\n  tmpvar_2.xyz = texture (sampler_main, uv_orig).xyz;\n  vec4 tmpvar_3;\n  tmpvar_3.w = 1.0;\n  tmpvar_3.xyz = mix (tmpvar_2, (texture (sampler_fc_main, (0.5 + \n    (((1.0 - abs(\n      ((fract((uv * 0.5)) * 2.0) - 1.0)\n    )) - 0.5) * (0.12 + pow ((1.0 - \n      sqrt(dot (x_1, x_1))\n    ), 0.2)))\n  )) - 0.04), vec4(0.7, 0.7, 0.7, 0.7)).xyz;\n  ret = tmpvar_3.xyz;\n}\n\n","comp":"shader_body\n{\n  vec4 tmpvar_1;\n  tmpvar_1.w = 1.0;\n  tmpvar_1.xyz = texture (sampler_main, uv).xyz;\n  ret = tmpvar_1.xyz;\n}\n\n"}