{"baseVals":{"rating":5,"decay":1,"echo_zoom":1,"echo_alpha":0.5,"echo_orient":3,"invert":1,"wave_a":0.001,"warpanimspeed":100,"warpscale":0.01,"zoomexp":1.14947,"warp":0,"sx":0.9901,"sy":0.9901,"wave_r":0,"wave_g":0,"wave_b":0,"ob_size":0,"ob_r":1,"ob_g":1,"ob_b":1,"ib_r":1,"ib_g":1,"ib_b":1,"mv_a":0},"shapes":[{"baseVals":{"enabled":0}},{"baseVals":{"enabled":0}},{"baseVals":{"enabled":0}},{"baseVals":{"enabled":1,"sides":100,"g":1,"b":1,"r2":1,"b2":1,"border_a":0},"init_eqs_str":"a.q4=0;a.q3=0;a.q4=0;a.xx=0;a.q4=0;a.yy=0;a.q4=0;a.radi=0;a.q4=0;a.q3=0;a.q3=0;a.radi=0;a.xx=0;a.yy=0;a.q1=0;a.q1=0;a.q1=0;a.q1=0;a.q1=0;a.q1=0;","frame_eqs_str":"a.a=above(a.q4,1E3-div(9E3,a.fps))&&above(a.q3,1.5)?1:0;a.a2=above(a.q4,1E3-div(3,a.fps));a.xx=(above(a.q4,1E3-div(3,a.fps)),.01*randint(100));a.yy=.00001<Math.abs(above(a.q4,1E3-div(3,a.fps)))?.01*randint(100):.01*randint(70)+.15;a.radi=.00001<Math.abs(above(a.q4,1E3-div(3,a.fps)))?.4*sqrt(a.q3)+.08:.5*sqrt(a.q3);a.rad=a.radi;a.x=a.xx;a.y=a.yy;a.r=.5*Math.sin(1.22*a.q1)+.6;a.g=.45+.45*Math.sin(1.307*a.q1);a.b=.45+.45*Math.sin(1.959*a.q1);a.r2=.5*Math.sin(1.622*a.q1)+.6;a.g2=\n.45+.45*Math.sin(1.507*a.q1);a.b2=.45+.45*Math.sin(1.6559*a.q1);"}],"waves":[{"baseVals":{"enabled":1,"spectrum":1,"thick":1,"a":0.42},"init_eqs_str":"a.zs=0;a.speed=0;a.q3=0;a.q4=0;a.q8=0;a.q30=0;a.q29=0;","frame_eqs_str":"","point_eqs_str":"a.zs=.00001<Math.abs(below(a.zs,1))?9:a.zs;a.zs=.00001<Math.abs(above(a.zs,1100))?1:a.zs;a.speed=div(.005*a.q3*(a.bass+a.mid+a.treb),3);a.zs+=Math.tan(a.q4)*Math.tan(a.speed);a.x=.5+(.18+.005*pow(a.q3,1.25))*Math.cos(div(75,a.q8)*a.zs);a.y=.5+(.18+.005*pow(a.q3,1.25))*Math.sin(div(75,a.q8)*a.zs);.00001<Math.abs(above(a.mid+a.treb,2*a.bass))?a.r=.3-Math.abs(.33*Math.sin(1-a.q3*a.bass)):a.r=.7+Math.abs(.33*Math.sin(1-a.q3*a.bass));.00001<Math.abs(above(a.bass+a.treb,2*a.mid))?\na.g=.3-Math.abs(.33*Math.sin(1-a.q30*a.mid*a.mid)):a.g=.7+Math.abs(.33*Math.sin(1-a.q30*a.mid*a.mid));.00001<Math.abs(below(a.mid+a.bass,2*a.treb))?a.b=.3-Math.abs(.33*Math.sin(1-a.q29*a.treb)):a.b=.7+Math.abs(.33*Math.sin(1-a.q29*a.treb));a.a=.175+.0007*a.q4;"},{"baseVals":{"enabled":0}},{"baseVals":{"enabled":0}},{"baseVals":{"enabled":0}}],"init_eqs_str":"a.foo_r=0;a.maxs=0;a.n=0;a.foo=0;a.ampl=0;a.bd_minbpm=0;a.im=0;a.basstime=0;a.bd_mean=0;a.timediff=0;a.bd_src=0;a.bd_slot=0;a.bd_b=0;a.bd_oct=0;a.tcos=0;a.stickybit=0;a.bd_arg=0;a.quali=0;a.q12=0;a.foo_b=0;a.q22=0;a.q21=0;a.volavg2=0;a.q13=0;a.q29=0;a.dt=0;a.bd_pk=0;a.maxo=0;a.bd_m=0;a.q1=0;a.bd_cos=0;a.q5=0;a.foo_g=0;a.sample1=0;a.difftime=0;a.dec_s=0;a.bd_exc=0;a.dec_xs=0;a.kraft=0;a.diff=0;a.bd_ampl=0;a.bd_mid_=0;a.maxind=0;a.edge=0;a.tsin=0;a.re0=0;a.testi=0;a.ec_steps=\n0;a.creep=0;a.q31=0;a.bpm=0;a.q23=0;a.q24=0;a.q11=0;a.bd_bass_=0;a.bd_tab0=0;a.show=0;a.dec_m=0;a.q4=0;a.im0=0;a.bd_spo=0;a.test0=0;a.bd_nres=0;a.bd_bass=0;a.maxa=0;a.volavg=0;a.feder=0;a.bd_recsz=0;a.bit2=0;a.tstart=0;a.bd_omega=0;a.bd_treb_=0;a.beatsin=0;a.bd_tabptr=0;a.bd_treb=0;a.q19=0;a.beat=0;a.vol=0;a.bd_mid=0;a.bd_dat0=0;a.prog=0;a.re=0;a.bd_t=0;a.beatcos=0;a.q2=0;a.time_st=0;a.bd_maxbpm=0;a.bd_qual=0;a.vol2=0;a.q3=0;a.t0=0;a.vol_=0;a.m=0;a.oct=0;a.quad=0;a.q32=0;a.basssum=0;a.creepo=0;a.q28=\n0;a.bd_sin=0;a.sample2=0;a.q30=0;a.change=0;a.beatct=0;a.q20=0;a.q8=0;a.bd_finc=0;for(var b=a.index=0;2E5>b;b++)a.megabuf[a.index]=0,a.gmegabuf[a.index]=0,a.index+=1;a.tstart=a.time;a.bd_recsz=8;a.bd_oct=4;a.bd_spo=30;a.bd_finc=pow(2,div(1,a.bd_spo));a.bd_nres=a.bd_oct*a.bd_spo;a.bd_minbpm=20;a.bd_maxbpm=pow(2,a.bd_oct)*a.bd_minbpm;a.bd_dat0=1E5;a.bd_tab0=a.bd_dat0+a.bd_nres*a.bd_recsz*3;a.reg00=a.bd_minbpm;a.reg01=a.bd_maxbpm;a.reg02=a.bd_recsz;a.reg03=a.bd_nres;a.reg05=a.bd_finc;a.reg06=a.bd_dat0;\na.reg07=a.bd_mp0;a.time_st=0;a.timediff=1;","frame_eqs_str":"a.dt=Math.min(div(1,a.fps),.1);a.dec_m=1-4*a.dt;a.dec_s=1-a.dt;a.dec_xs=1-div(a.dt,6);a.t0=a.time-a.tstart;a.bd_b=a.bass;a.bd_bass_=a.bd_bass_*a.dec_m+(1-a.dec_m)*a.bd_b;a.bd_bass=a.bd_b-a.bd_bass_;a.bd_m=a.mid;a.bd_mid_=a.bd_mid_*a.dec_m+(1-a.dec_m)*a.bd_m;a.bd_mid=a.bd_m-a.bd_mid_;a.bd_t=a.treb;a.bd_treb_=a.bd_treb_*a.dec_m+(1-a.dec_m)*a.bd_t;a.bd_treb=a.bd_t-a.bd_treb_;a.n=0;a.bpm=a.bd_minbpm;for(var b=0;b<a.bd_nres;b++)a.gmegabuf[5E4+a.n*a.bd_recsz]=0,a.bd_arg=div(a.bpm,\n60)*a.t0*6.283,a.gmegabuf[a.bd_tab0+a.n*a.bd_recsz]=a.bpm,a.bpm*=a.bd_finc,a.n+=1;for(b=a.bd_src=0;3>b;b++){a.bd_exc=a.bd_bass*(.00001>Math.abs(a.bd_src-0)?1:0)+a.bd_mid*(.00001>Math.abs(a.bd_src-1)?1:0)+a.bd_treb*(.00001>Math.abs(a.bd_src-2)?1:0);for(var c=a.oct=0;c<a.bd_oct;c++){a.bd_slot=0;a.bd_pk=0;for(var d=a.bd_mean=0;d<a.bd_spo;d++){a.bd_tabptr=a.bd_tab0+(a.oct*a.bd_spo+a.bd_slot)*a.bd_recsz;a.n=a.bd_dat0+(a.bd_nres*a.bd_src+a.oct*a.bd_spo+a.bd_slot)*a.bd_recsz;a.bpm=a.gmegabuf[a.bd_tabptr];\na.bd_omega=6.283*div(a.bpm,60);a.feder=sqr(a.bd_omega);a.gmegabuf[a.n+4]=a.gmegabuf[a.n+2];a.gmegabuf[a.n+1]*=1-.5*a.dt*sqrt(div(a.bpm,300));a.ec_steps=2*Math.floor(1+div(a.bpm,50));for(var e=0;e<a.ec_steps;e++)a.kraft=a.bd_exc-a.feder*a.gmegabuf[a.n+2],a.gmegabuf[a.n+1]+=div(a.kraft*a.dt,a.ec_steps),a.gmegabuf[a.n+2]+=div(a.gmegabuf[a.n+1]*a.dt,a.ec_steps);a.beatcos=a.gmegabuf[a.n+1];a.beatsin=a.gmegabuf[a.n+2]*a.bd_omega;a.quad=sqrt(pow(a.beatsin,2)+pow(a.beatcos,2));a.gmegabuf[a.n]=.8*a.gmegabuf[a.n]+\n.2*a.quad;a.bd_ampl=a.gmegabuf[a.n];a.bd_mean+=a.bd_ampl;.00001<Math.abs(a.bd_ampl>a.bd_pk?1:0)?a.bd_pk=a.bd_ampl:0;a.bd_slot+=1}a.bd_slot=0;a.bd_qual=pow(div(a.bd_pk,a.bd_mean)*a.bd_spo-1,1);a.gmegabuf[2*(a.bd_src*a.bd_oct+a.oct)]=a.bd_qual;for(d=0;d<a.bd_spo;d++)a.m=5E4+(a.bd_slot+0*a.oct*a.bd_spo)*a.bd_recsz,a.n=a.bd_dat0+(a.bd_nres*a.bd_src+a.oct*a.bd_spo+a.bd_slot)*a.bd_recsz,a.gmegabuf[a.m]+=div(a.bd_qual*a.gmegabuf[a.n],12),a.bd_slot+=1;a.oct+=1}a.bd_src+=1}a.bd_slot=0;a.maxind=0;a.bd_pk=0;\nfor(b=a.bd_mean=0;b<a.bd_spo;b++)a.m=5E4+a.bd_slot*a.bd_recsz,a.gmegabuf[a.m]=pow(a.gmegabuf[a.m],1),a.bd_mean+=a.gmegabuf[a.m],.00001<Math.abs(a.gmegabuf[a.m]>a.bd_pk?1:0)?(a.bd_pk=a.gmegabuf[a.m],a.maxind=a.bd_slot):0,a.bd_slot+=1;a.quali=div(a.bd_pk,a.bd_mean)*a.bd_spo-1;for(b=a.n=0;150>b;b++)a.gmegabuf[50+a.n]*=0,a.n+=1;a.bd_src=0;a.tsin=0;for(b=a.tcos=0;3>b;b++){for(c=a.oct=0;c<a.bd_oct;c++)a.n=a.bd_dat0+(a.bd_nres*a.bd_src+a.oct*a.bd_spo+a.maxind)*a.bd_recsz,a.bd_tabptr=a.bd_tab0+(a.oct*a.bd_spo+\na.maxind)*a.bd_recsz,a.bpm=a.gmegabuf[a.bd_tabptr],a.im=a.gmegabuf[a.n+1],a.re=6.283*div(a.gmegabuf[a.n+2]*a.bpm,60),a.bd_cos=Math.cos(6.28*div(a.bpm,60)*a.time),a.bd_sin=-Math.sin(6.28*div(a.bpm,60)*a.time),a.re0=a.re*a.bd_cos+a.im*a.bd_sin,a.im0=-a.re*a.bd_sin+a.im*a.bd_cos,a.bd_qual=a.gmegabuf[2*(a.bd_src*a.bd_oct+a.oct)],a.gmegabuf[50+4*a.oct]+=a.bd_qual*a.im0,a.gmegabuf[4*a.oct+51]+=a.bd_qual*a.re0,a.gmegabuf[4*a.oct+52]+=a.bd_qual,a.gmegabuf[100]+=a.bd_qual*a.im0,a.gmegabuf[101]+=a.bd_qual*\na.re0,a.re=a.bd_cos*a.re0+a.bd_sin*a.im0,a.im=-a.bd_cos*a.im0+a.bd_sin*a.re0,a.tsin+=5*a.im,a.oct+=1;a.bd_src+=1}a.q30=a.tsin;a.vol=a.bass_att+a.mid_att+a.treb_att;a.vol_=.95*a.vol_+.05*a.vol;a.q29=a.vol-a.vol_;a.bd_src=0;a.maxo=0;a.maxs=0;for(b=a.maxa=0;3>b;b++){a.oct=1;for(c=0;c<a.bd_oct-1;c++)a.n=a.bd_dat0+(a.bd_nres*a.bd_src+a.oct*a.bd_spo+a.maxind)*a.bd_recsz,a.bd_qual=a.gmegabuf[2*(a.bd_src*a.bd_oct+a.oct)],a.ampl=div(a.bd_qual,1+a.oct*div(a.maxind,a.bd_oct)*0),.00001<Math.abs(a.ampl>a.maxa?\n1:0)?(a.maxa=a.ampl,a.maxs=a.bd_src,a.maxo=a.oct):0,a.oct+=1;a.bd_src+=1}a.q28=pow(4*a.bd_qual,1.5);a.q31=a.q28;.00001<Math.abs(above(a.q28,65))?a.q28=pow(5*Math.sin(.5*a.bd_qual),2):0;a.monitor=a.q28;a.testi=a.bd_nres*a.maxs+a.bd_spo*a.maxo+a.maxind;.00001<Math.abs(bor(a.beat&&.00001>Math.abs(a.prog-0)?1:0,2>Math.abs(a.testi-a.test0)?1:0))?a.test0=a.testi:0;a.n=a.bd_dat0+a.test0*a.bd_recsz;a.creep=a.gmegabuf[a.n+1];a.beat=(0<a.creep?1:0)*(0>a.creepo?1:0);a.beatct=.00001<Math.abs(a.change)?0:a.beatct+\na.beat;a.prog=mod(a.prog+a.beat,8);a.creepo=a.creep;a.show=.00001<Math.abs(a.beat)?1:.5*a.show;a.q4=1E3*div(a.gmegabuf[a.n+1],a.gmegabuf[a.n]);a.q2=a.prog;.00001<Math.abs(a.beat)?(a.timediff=a.time-a.time_st,a.time_st=a.time):a.timediff=a.timediff;.00001<Math.abs(below(a.timediff,.0625))?a.timediff=.0625:a.timediff=a.timediff;a.q8=a.timediff;a.q24=a.bd_maxbpm;a.basstime+=div(3*a.bass,a.fps);a.q1=a.basstime;a.basstime=.00001<Math.abs(below(a.basstime,1E3))?1E3:a.basstime;a.basstime=.00001<Math.abs(above(a.basstime,\n10004))?1E3:a.basstime;a.basstime+=div(.75*a.bass_att,a.fps);a.vol2=pow(a.bass+a.mid+a.treb,2);a.basssum=a.vol2;a.stickybit=mod(a.time,2);a.volavg+=a.vol2*equal(a.stickybit,1);a.sample1+=equal(a.stickybit,1);a.volavg2+=a.vol2*equal(a.stickybit,0);a.sample2+=equal(a.stickybit,0);a.edge=bnot(equal(a.bit2,a.stickybit));a.volavg-=a.volavg*a.edge*a.stickybit;a.volavg2-=a.volavg2*a.edge*equal(a.stickybit,0);a.sample1-=a.sample1*a.edge*a.stickybit;a.sample2-=a.sample2*a.edge*equal(a.stickybit,0);a.diff=\n.00001<Math.abs(equal(a.stickybit,1))?div(a.basssum,div(a.volavg2,a.sample2)):0;a.diff=.00001<Math.abs(equal(a.stickybit,0))?div(a.basssum,div(a.volavg,a.sample1)):a.diff;a.q3=a.diff;a.q32=.9328*a.q32+.0666*a.q3*(a.bass_att*a.bass_att+a.treb_att*a.treb_att)*.0005*a.q4;a.bit2=mod(a.time,2);a.difftime+=.03*a.diff;a.q2=a.difftime;a.warp=.005*(a.bass*a.bass+a.mid*a.mid+a.treb*a.treb);a.foo_r=Math.sin(.4575*a.q1);a.foo_g=Math.sin(.49*a.q1);a.foo_b=Math.sin(.7346*a.q1);.00001<Math.abs(above(a.foo_r,a.foo_g)&&\nabove(a.foo_r,a.foo_b)?1:0)?a.q23=1:a.q23=0;.00001<Math.abs(above(a.foo_g,a.foo_r)&&above(a.foo_g,a.foo_b)?1:0)?a.q21=1:a.q21=0;.00001<Math.abs(above(a.foo_b,a.foo_r)&&above(a.foo_b,a.foo_g)?1:0)?a.q22=1:a.q22=0;.00001<Math.abs(equal(a.q11+a.q12+a.q13,0))?a.q22=1:0;a.q5=div(30,a.fps);a.q19=1+10*a.q8;a.q20=1.1;.00001<Math.abs(above(a.q31,12))?a.q19=7+.333*a.q31:a.q19=a.q19;.00001<Math.abs(above(a.q31,55))?(.00001<Math.abs(above(a.q3,3.5))?(a.foo=1+div(.333,a.bass_att*a.bass_att*a.bass_att),a.q20=3E4):\na.foo=a.foo,.00001<Math.abs(above(a.bass_att+a.mid_att+a.treb_att,2.5))?(a.q19=a.foo,a.q20=3E4):a.q19=a.q19):a.q19=a.q19;.00001<Math.abs(above(a.q3,1.4))?a.q19=1.5+10*a.q8:a.q19=a.q19;","pixel_eqs_str":"a.zoom=a.q19;a.zoomexp=a.q20;a.rot=0;","warp":" shader_body { \n  vec3 ret_1;\n  ret_1 = ((texture (sampler_blur2, texture (sampler_fc_main, uv_orig).xy).xyz * scale2) + bias2);\n  vec2 tmpvar_2;\n  tmpvar_2 = (((texsize.zw * q5) * 6.0) * pow ((\n    (ret_1.x * ret_1.y)\n   * ret_1.z), 0.333));\n  vec3 tmpvar_3;\n  tmpvar_3 = (((texture (sampler_blur1, \n    (uv_orig + (vec2(1.0, 0.0) * tmpvar_2))\n  ).xyz * scale1) + bias1) - ((texture (sampler_blur1, \n    (uv_orig - (vec2(1.0, 0.0) * tmpvar_2))\n  ).xyz * scale1) + bias1));\n  vec3 tmpvar_4;\n  tmpvar_4 = (((texture (sampler_blur1, \n    (uv_orig + (vec2(0.0, 1.0) * tmpvar_2))\n  ).xyz * scale1) + bias1) - ((texture (sampler_blur1, \n    (uv_orig - (vec2(0.0, 1.0) * tmpvar_2))\n  ).xyz * scale1) + bias1));\n  vec2 tmpvar_5;\n  tmpvar_5.x = tmpvar_3.x;\n  tmpvar_5.y = tmpvar_4.x;\n  vec2 tmpvar_6;\n  tmpvar_6.x = tmpvar_3.y;\n  tmpvar_6.y = tmpvar_4.y;\n  vec2 tmpvar_7;\n  tmpvar_7.x = tmpvar_3.z;\n  tmpvar_7.y = tmpvar_4.z;\n  vec2 tmpvar_8;\n  tmpvar_8 = (uv_orig + ((\n    (((tmpvar_5 * q21) + (tmpvar_6 * q22)) + (tmpvar_7 * q23))\n   * texsize.zw) * 6.0));\n  vec4 tmpvar_9;\n  tmpvar_9 = texture (sampler_main, uv_orig);\n  ret_1 = ((texture (sampler_main, tmpvar_8).xyz + (\n    (texture (sampler_main, uv).xyz - ((texture (sampler_blur1, uv).xyz * scale1) + bias1))\n   * 0.1)) - ((0.0006 * q28) * (\n    ((((\n      (tmpvar_9.x * tmpvar_9.y)\n     * tmpvar_9.z) / q8) + ((\n      sqrt(treb)\n     * tmpvar_9.x) * tmpvar_9.y)) + ((sqrt(mid) * tmpvar_9.x) * tmpvar_9.z))\n   + \n    ((sqrt(bass) * tmpvar_9.y) * tmpvar_9.z)\n  )));\n  ret_1.x = mix (ret_1.x, (1.025 * texture (sampler_pc_main, tmpvar_8).x), (bass_att * 0.1));\n  ret_1.y = mix (ret_1.y, (1.025 * texture (sampler_pc_main, tmpvar_8).y), (mid_att * 0.1));\n  ret_1.z = mix (ret_1.z, (1.025 * texture (sampler_pc_main, tmpvar_8).z), (treb_att * 0.1));\n  ret_1 = (ret_1 + ((\n    (pow (q3, 1.3) - 0.333)\n   * 0.00666) * texture (sampler_pw_main, uv_orig)).xyz);\n  vec4 tmpvar_10;\n  tmpvar_10.w = 1.0;\n  tmpvar_10.xyz = ret_1;\n  ret = tmpvar_10.xyz;\n }","comp":" shader_body { \n  vec3 ret_1;\n  ret_1 = mix (texture (sampler_main, uv).xyz, texture (sampler_main, ((0.5 - uv) + 0.5)).xyz, vec3(0.5, 0.5, 0.5));\n  ret_1 = (1.0 - ((ret_1 * \n    (1.0 - ret_1)\n  ) * 4.0));\n  vec4 tmpvar_2;\n  tmpvar_2.w = 1.0;\n  tmpvar_2.xyz = ret_1;\n  ret = tmpvar_2.xyz;\n }"}